thermosmart_hass/__init__.py
thermosmart_hass/oauth2.py
thermosmart_hass/test.py
thermosmart_hass/thermosmart_api.py
thermosmart_hass-0.6.4.dist-info/METADATA
thermosmart_hass-0.6.4.dist-info/WHEEL
thermosmart_hass-0.6.4.dist-info/top_level.txt
thermosmart_hass-0.6.4.dist-info/RECORD
